neurorosettes/__init__.py
neurorosettes/clocks.py
neurorosettes/config.py
neurorosettes/grid.py
neurorosettes/neurons.py
neurorosettes/physics.py
neurorosettes/simulation.py
neurorosettes/subcellular.py
neurorosettes/utilities.py
neurorosettes-0.1.1.dist-info/entry_points.txt
neurorosettes-0.1.1.dist-info/LICENSE
neurorosettes-0.1.1.dist-info/WHEEL
neurorosettes-0.1.1.dist-info/METADATA
neurorosettes-0.1.1.dist-info/RECORD
