Metadata-Version: 2.1
Name: neurorosettes
Version: 0.1.1
Summary: A computational modelling framework designed to simulate the formation of rosette patterns in tissues of the nervous system.
License: BSD-3-Clause
Author: Inês G Gonçalves
Requires-Python: >=3.7,<4.0
Classifier: License :: OSI Approved :: BSD License
Classifier: Programming Language :: Python :: 3
Classifier: Programming Language :: Python :: 3.10
Classifier: Programming Language :: Python :: 3.7
Classifier: Programming Language :: Python :: 3.8
Classifier: Programming Language :: Python :: 3.9
Requires-Dist: click (>=8.0.4,<9.0.0)
Requires-Dist: pydantic (>=1.9.0,<2.0.0)
Requires-Dist: vedo (>=2022.0.1,<2023.0.0)
